README.rst
setup.cfg
setup.py
datatank_py/DTBitmap2D.py
datatank_py/DTDataFile.py
datatank_py/DTError.py
datatank_py/DTMask.py
datatank_py/DTMesh2D.py
datatank_py/DTPath2D.py
datatank_py/DTPathValues2D.py
datatank_py/DTPlot1D.py
datatank_py/DTPoint2D.py
datatank_py/DTPointCollection2D.py
datatank_py/DTPointValue2D.py
datatank_py/DTPointValueCollection2D.py
datatank_py/DTProgress.py
datatank_py/DTPyCoreImage.py
datatank_py/DTPyWrite.py
datatank_py/DTRegion2D.py
datatank_py/DTRegion3D.py
datatank_py/DTSeries.py
datatank_py/DTStructuredGrid2D.py
datatank_py/DTStructuredGrid3D.py
datatank_py/DTStructuredMesh2D.py
datatank_py/DTStructuredMesh3D.py
datatank_py/DTStructuredVectorField2D.py
datatank_py/DTStructuredVectorField3D.py
datatank_py/DTTriangularGrid2D.py
datatank_py/DTTriangularMesh2D.py
datatank_py/DTTriangularVectorField2D.py
datatank_py/DTVector2D.py
datatank_py/__init__.py
datatank_py.egg-info/PKG-INFO
datatank_py.egg-info/SOURCES.txt
datatank_py.egg-info/dependency_links.txt
datatank_py.egg-info/not-zip-safe
datatank_py.egg-info/requires.txt
datatank_py.egg-info/top_level.txt