Metadata-Version: 1.0
Name: datatank-py
Version: 0.6
Summary: Module for reading and writing DataTank files
Home-page: http://github.com/amaxwell/datatank_py
Author: Adam R. Maxwell
Author-email: amaxwell@mac.com
License: BSD New
Download-URL: http://github.com/amaxwell/datatank_py/tarball/0.6
Platform: UNKNOWN
Classifier: Development Status :: 5 - Production/Stable
Classifier: Environment :: Console
Classifier: Intended Audience :: Developers
Classifier: Intended Audience :: End Users/Desktop
Classifier: License :: OSI Approved :: BSD License
Classifier: Operating System :: MacOS :: MacOS X
Classifier: Operating System :: Microsoft
Classifier: Operating System :: POSIX
Classifier: Topic :: Scientific/Engineering :: Visualization
Classifier: Topic :: Software Development :: Libraries :: Python Modules
